README.md
setup.py
ultramiko/__init__.py
ultramiko/main.py
ultramiko.egg-info/PKG-INFO
ultramiko.egg-info/SOURCES.txt
ultramiko.egg-info/dependency_links.txt
ultramiko.egg-info/top_level.txt